Metadata-Version: 1.2
Name: chatbot-py
Version: 2.72
Summary: 中文聊天机器人， 根据自己的语料训练出自己想要的聊天机器人，可以用于智能客服、在线问答、智能聊天等场景!
Home-page: https://github.com/lin423497786/chatbot-py
Author: lb
Author-email: 423497786@qq.com
License: UNKNOWN
Keywords: chatbot
Platform: any
Requires-Python: >=3.4, <4
